cirq_pasqal/__init__.py
cirq_pasqal/_version.py
cirq_pasqal/_version_test.py
cirq_pasqal/conftest.py
cirq_pasqal/json_resolver_cache.py
cirq_pasqal/pasqal_device.py
cirq_pasqal/pasqal_device_test.py
cirq_pasqal/pasqal_gateset.py
cirq_pasqal/pasqal_gateset_test.py
cirq_pasqal/pasqal_noise_model.py
cirq_pasqal/pasqal_noise_model_test.py
cirq_pasqal/pasqal_qubits.py
cirq_pasqal/pasqal_qubits_test.py
cirq_pasqal/pasqal_sampler.py
cirq_pasqal/pasqal_sampler_test.py
cirq_pasqal/json_test_data/PasqalDevice.json
cirq_pasqal/json_test_data/PasqalDevice.json_inward
cirq_pasqal/json_test_data/PasqalDevice.repr
cirq_pasqal/json_test_data/PasqalDevice.repr_inward
cirq_pasqal/json_test_data/PasqalGateset.json
cirq_pasqal/json_test_data/PasqalGateset.repr
cirq_pasqal/json_test_data/PasqalVirtualDevice.json
cirq_pasqal/json_test_data/PasqalVirtualDevice.json_inward
cirq_pasqal/json_test_data/PasqalVirtualDevice.repr
cirq_pasqal/json_test_data/PasqalVirtualDevice.repr_inward
cirq_pasqal/json_test_data/ThreeDQubit.json
cirq_pasqal/json_test_data/ThreeDQubit.json_inward
cirq_pasqal/json_test_data/ThreeDQubit.repr
cirq_pasqal/json_test_data/ThreeDQubit.repr_inward
cirq_pasqal/json_test_data/TwoDQubit.json
cirq_pasqal/json_test_data/TwoDQubit.json_inward
cirq_pasqal/json_test_data/TwoDQubit.repr
cirq_pasqal/json_test_data/TwoDQubit.repr_inward
cirq_pasqal/json_test_data/__init__.py
cirq_pasqal/json_test_data/spec.py
cirq_pasqal-1.6.0.dist-info/licenses/LICENSE
cirq_pasqal-1.6.0.dist-info/METADATA
cirq_pasqal-1.6.0.dist-info/WHEEL
cirq_pasqal-1.6.0.dist-info/top_level.txt
cirq_pasqal-1.6.0.dist-info/RECORD
